genesisapi/__init__.py
genesisapi/client.py
genesisapi/datatypes.py
genesisapi/endpoint.py
genesisapi/result.py
genesisapi/services/__init__.py
genesisapi/services/catalogue.py
genesisapi/services/data.py
genesisapi/services/find.py
genesisapi/services/helloworld.py
genesisapi/services/metadata.py
genesisapi/services/profile.py
genesisapi/table.py
genesisapi-0.1.0.dist-info/LICENSE
genesisapi-0.1.0.dist-info/WHEEL
genesisapi-0.1.0.dist-info/METADATA
genesisapi-0.1.0.dist-info/RECORD
