Metadata-Version: 2.1
Name: genesisapi
Version: 0.1.0
Summary: 
Author: Roland Abel
Author-email: roland.abel@live.de
Requires-Python: >=3.9,<4.0
Classifier: Programming Language :: Python :: 3
Classifier: Programming Language :: Python :: 3.10
Classifier: Programming Language :: Python :: 3.9
Requires-Dist: pandas (>=1.4.0,<2.0.0)
Requires-Dist: typeguard (>=2.13.3,<3.0.0)
